llm_layer_collector/__init__.py
llm_layer_collector/cache.py
llm_layer_collector/compute.py
llm_layer_collector/helpers.py
llm_layer_collector/layer_collector.py
llm_layer_collector/load_layer.py
llm_layer_collector/state_obj.py
llm_layer_collector/auto/auto_layer.py
llm_layer_collector/auto/auto_rms.py
llm_layer_collector/auto/auto_rotary.py
llm_layer_collector-0.1.7.dist-info/METADATA
llm_layer_collector-0.1.7.dist-info/WHEEL
llm_layer_collector-0.1.7.dist-info/licenses/LICENSE
llm_layer_collector-0.1.7.dist-info/RECORD
