Metadata-Version: 2.4
Name: llm-layer-collector
Version: 0.1.7
Summary: A tool for loading and computing on parts of LLM models.
Project-URL: Homepage, https://github.com/erinclemmer/llm-layer-collector
Project-URL: Issues, https://github.com/erinclemmer/llm-layer-collector/issues
Author-email: Erin Clemmer <erin.c.clemmer@gmail.com>
License-Expression: MIT
License-File: LICENSE
Keywords: llm,safetensors,torch,transformers
Classifier: Development Status :: 5 - Production/Stable
Classifier: Intended Audience :: Science/Research
Classifier: License :: OSI Approved :: MIT License
Classifier: Operating System :: OS Independent
Classifier: Programming Language :: Python :: 3.10
Classifier: Topic :: Scientific/Engineering :: Artificial Intelligence
Classifier: Typing :: Typed
Requires-Python: >=3.10
Requires-Dist: protobuf
Requires-Dist: safetensors
Requires-Dist: torch
Requires-Dist: tqdm
Requires-Dist: transformers
